honeyxiong/__init__.py
honeyxiong/brands.py
honeyxiong/main.py
honeyxiong/plates.py
honeyxiong/utils.py
honeyxiong-0.1.1.dist-info/METADATA
honeyxiong-0.1.1.dist-info/WHEEL
honeyxiong-0.1.1.dist-info/top_level.txt
honeyxiong-0.1.1.dist-info/RECORD
