Metadata-Version: 2.1
Name: honeyxiong
Version: 0.1.1
Summary: Генератор автомобильных марок и номеров
Author: JM
Classifier: Programming Language :: Python :: 3
Classifier: License :: OSI Approved :: MIT License
Classifier: Operating System :: OS Independent
Requires-Python: >=3.6
